{
  "step2-high-priority-features": {
    "phase": "archived",
    "matchRate": 93.4,
    "iterationCount": 2,
    "startedAt": "2026-02-15T10:00:00Z",
    "completedAt": "2026-02-16T09:30:00Z",
    "archivedAt": "2026-02-16T10:00:00Z",
    "archivedTo": "docs/archive/2026-02/step2-high-priority-features/",
    "summary": {
      "services": 4,
      "apis": 16,
      "frontendFiles": 3,
      "improvements": 20,
      "gapsTotal": 15,
      "gapsResolved": 13,
      "performanceGains": {
        "autocomplete": "75%",
        "search": "40%",
        "backup": "25%"
      }
    }
  }
}
